{
  "key": 6,
  "demands": [
    4000,
    4000,
    6000,
    75,
    1200,
    56,
    55
  ],
  "durs": [
    3,
    1,
    2,
    5,
    1,
    5,
    5
  ],
  "ests": [
    0,
    0,
    0,
    0,
    0,
    0,
    0
  ],
  "lfts": [
    146,
    144,
    145,
    148,
    144,
    148,
    148
  ],
  "psts": [
    55,
    134,
    29,
    125,
    56,
    77,
    103
  ],
  "cfs": [
    3,
    1,
    7,
    1,
    5,
    9,
    6
  ],
  "precs": {},
  "succ_delays": {},
  "no_prec": 0,
  "demand": {
    "preferred": [
      0,
      0,
      0,
      0,
      0,
      0,
      0,
      0,
      0,
      0,
      0,
      0,
      0,
      0,
      0,
      0,
      0,
      0,
      0,
      0,
      0,
      0,
      0,
      0,
      0,
      0,
      0,
      0,
      0,
      6000,
      6000,
      0,
      0,
      0,
      0,
      0,
      0,
      0,
      0,
      0,
      0,
      0,
      0,
      0,
      0,
      0,
      0,
      0,
      0,
      0,
      0,
      0,
      0,
      0,
      0,
      4000,
      5200,
      4000,
      0,
      0,
      0,
      0,
      0,
      0,
      0,
      0,
      0,
      0,
      0,
      0,
      0,
      0,
      0,
      0,
      0,
      0,
      0,
      56,
      56,
      56,
      56,
      56,
      0,
      0,
      0,
      0,
      0,
      0,
      0,
      0,
      0,
      0,
      0,
      0,
      0,
      0,
      0,
      0,
      0,
      0,
      0,
      0,
      0,
      55,
      55,
      55,
      55,
      55,
      0,
      0,
      0,
      0,
      0,
      0,
      0,
      0,
      0,
      0,
      0,
      0,
      0,
      0,
      0,
      0,
      0,
      75,
      75,
      75,
      75,
      75,
      0,
      0,
      0,
      0,
      4000,
      0,
      0,
      0,
      0,
      0,
      0,
      0,
      0,
      0
    ],
    "max": 6000,
    "limit": 6000
  },
  "start_times": {
    "heuristic": {
      "0": [
        55,
        134,
        29,
        125,
        56,
        77,
        103
      ]
    }
  },
  "cost": {},
  "inconvenient": {},
  "objective": {}
}